bsdk/__init__.py
bsdk/core.py
bsdk/list_of_practical.py
bsdk/practical_files/clustering.txt
bsdk/practical_files/decision_tree.txt
bsdk/practical_files/linear_regression.txt
bsdk/practical_files/logistic_regression.txt
bsdk/practical_files/svm.txt
bsdk-0.0.1.dist-info/licenses/LICENSE
bsdk-0.0.1.dist-info/METADATA
bsdk-0.0.1.dist-info/WHEEL
bsdk-0.0.1.dist-info/entry_points.txt
bsdk-0.0.1.dist-info/top_level.txt
bsdk-0.0.1.dist-info/RECORD
