Metadata-Version: 2.4
Name: bsdk
Version: 0.0.1
Summary: Easy to copy package
Author: Unknown
Author-email: rugvedapraj1@gmail.com
Classifier: Programming Language :: Python :: 3
Classifier: Operating System :: OS Independent
Requires-Python: >=3.6
License-File: LICENSE
Dynamic: author
Dynamic: author-email
Dynamic: classifier
Dynamic: license-file
Dynamic: requires-python
Dynamic: summary
